arcadia_microscopy_tools/__init__.py
arcadia_microscopy_tools/blending.py
arcadia_microscopy_tools/channels.py
arcadia_microscopy_tools/masks.py
arcadia_microscopy_tools/metadata_structures.py
arcadia_microscopy_tools/microplate.py
arcadia_microscopy_tools/microscopy.py
arcadia_microscopy_tools/model.py
arcadia_microscopy_tools/nikon.py
arcadia_microscopy_tools/operations.py
arcadia_microscopy_tools/pipeline.py
arcadia_microscopy_tools/typing.py
arcadia_microscopy_tools/utils.py
arcadia_microscopy_tools/tests/__init__.py
arcadia_microscopy_tools/tests/conftest.py
arcadia_microscopy_tools/tests/test_channels.py
arcadia_microscopy_tools/tests/test_microplate.py
arcadia_microscopy_tools/tests/test_microscopy.py
arcadia_microscopy_tools/tests/test_model.py
arcadia_microscopy_tools/tests/test_pipeline.py
arcadia_microscopy_tools/tests/data/README.md
arcadia_microscopy_tools/tests/data/example-cerevisiae.nd2
arcadia_microscopy_tools/tests/data/example-multichannel.nd2
arcadia_microscopy_tools/tests/data/example-pbmc.nd2
arcadia_microscopy_tools/tests/data/example-timelapse.nd2
arcadia_microscopy_tools/tests/data/example-zstack.nd2
arcadia_microscopy_tools/tests/data/known-metadata.yml
arcadia_microscopy_tools-0.2.4.dist-info/METADATA
arcadia_microscopy_tools-0.2.4.dist-info/WHEEL
arcadia_microscopy_tools-0.2.4.dist-info/licenses/LICENSE
arcadia_microscopy_tools-0.2.4.dist-info/RECORD
