Metadata-Version: 2.4
Name: arcadia-microscopy-tools
Version: 0.2.4
Summary: Python package for processing large-scale microscopy datasets generated by Arcadia's imaging suite
License: MIT License
License-File: LICENSE
Requires-Python: >=3.12
Requires-Dist: arcadia-pycolor>=0.6.5
Requires-Dist: colour-science>=0.4.7
Requires-Dist: liffile>=2025.12.12
Requires-Dist: nd2>=0.10.3
Requires-Dist: numpy>=2.4.1
Requires-Dist: pandas>=2.3.3
Requires-Dist: scikit-image>=0.25.2
Provides-Extra: all
Requires-Dist: cellpose>=4.0.6; extra == 'all'
Requires-Dist: modal; extra == 'all'
Provides-Extra: compute
Requires-Dist: modal; extra == 'compute'
Provides-Extra: segmentation
Requires-Dist: cellpose>=4.0.6; extra == 'segmentation'
Requires-Dist: torch>=2.7.1; extra == 'segmentation'
